{"actionUrl":"https:\/\/asp.acs-tpkg.com\/ld","actionHostName":"https:\/\/asp.acs-tpkg.com","userId":"lp_sn","id":"2016110001","location":"https:\/\/www.perfectone.tw","changeThankyouPageUrl":true,"thankyouPageUrl":"https:\/\/www.perfectone.tw\/oto202205\/","thankyouPageUrlSingleProduct":null,"thankyouPageUrlRegularProduct":null,"thankyouPageUrlCod":null,"thankyouPageUrlConv":null,"convertType":"TWD","language":"tc","couponIsEnable":false,"receivingMethod":[{"1":true,"2":true,"8":true},{"1":true}],"defaultShippingDate":null,"endShippingDate":null,"shippingDateHide":false,"policy":"policy","questionIsEnable":false,"questionTitle":null,"questionIsRequired":null,"questionValue":[],"agreementIsEnable":false,"agreementTitle":null,"agreementOptionTitle":null,"productTopDescription":null,"productBottomDescription":"<span style='color: red;font-weight: bolder;'>※運費198元包含：日本跟台灣物流運輸＋包材作業處理費<br>※請注意：此為活動期間限定體驗瓶，恕不進行退換貨<\/span>","addressTopDescription":null,"addressBottomDescription":null,"phoneTopDescription":null,"phoneBottomDescription":null,"emailTopDescription":null,"emailBottomDescription":null,"receivingTopDescription":null,"receivingBottomDescription":null,"paymentTopDescription":null,"paymentBottomDescription":null,"shippingDateTopDescription":null,"shippingDateBottomDescription":null,"titleTopOtherMemo":null,"topOtherMemo":null,"titleBottomOtherMemo":null,"bottomOtherMemo":null}